{
  "sys": {
    "primary": {
      "value": "{color.primary.800}",
      "type": "color"
    },
    "on-primary": {
      "value": "{color.primary.200}",
      "type": "color"
    },
    "primary-container": {
      "value": "{color.primary.300}",
      "type": "color"
    },
    "on-primary-container": {
      "value": "{color.primary.900}",
      "type": "color"
    },
    "primary-fixed": {
      "value": "{color.primary.900}",
      "type": "color"
    },
    "on-primary-fixed": {
      "value": "{color.primary.100}",
      "type": "color"
    },
    "primary-fixed-dim": {
      "value": "{color.primary.800}",
      "type": "color"
    },
    "on-primary-fixed-variant": {
      "value": "{color.primary.300}",
      "type": "color"
    },
    "secondary": {
      "value": "{color.secondary.800}",
      "type": "color"
    },
    "on-secondary": {
      "value": "{color.secondary.200}",
      "type": "color"
    },
    "secondary-container": {
      "value": "{color.secondary.300}",
      "type": "color"
    },
    "on-secondary-container": {
      "value": "{color.secondary.900}",
      "type": "color"
    },
    "secondary-fixed": {
      "value": "{color.secondary.900}",
      "type": "color"
    },
    "on-secondary-fixed": {
      "value": "{color.secondary.100}",
      "type": "color"
    },
    "secondary-fixed-dim": {
      "value": "{color.secondary.800}",
      "type": "color"
    },
    "on-secondary-fixed-variant": {
      "value": "{color.secondary.300}",
      "type": "color"
    },
    "success": {
      "value": "{color.success.800}",
      "type": "color"
    },
    "on-success": {
      "value": "{color.success.200}",
      "type": "color"
    },
    "success-container": {
      "value": "{color.success.300}",
      "type": "color"
    },
    "on-success-container": {
      "value": "{color.success.900}",
      "type": "color"
    },
    "warning": {
      "value": "{color.warning.800}",
      "type": "color"
    },
    "on-warning": {
      "value": "{color.warning.200}",
      "type": "color"
    },
    "warning-container": {
      "value": "{color.warning.300}",
      "type": "color"
    },
    "on-warning-container": {
      "value": "{color.warning.900}",
      "type": "color"
    },
    "error": {
      "value": "{color.error.800}",
      "type": "color"
    },
    "on-error": {
      "value": "{color.error.200}",
      "type": "color"
    },
    "error-container": {
      "value": "{color.error.300}",
      "type": "color"
    },
    "on-error-container": {
      "value": "{color.error.900}",
      "type": "color"
    },
    "outline": {
      "value": "{color.neutral.600}",
      "type": "color"
    },
    "background": {
      "value": "{color.neutral.100}",
      "type": "color"
    },
    "on-background": {
      "value": "{color.neutral.900}",
      "type": "color"
    },
    "surface": {
      "value": "{color.neutral.60}",
      "type": "color"
    },
    "on-surface": {
      "value": "{color.neutral.800}",
      "type": "color"
    },
    "surface-variant": {
      "value": "{color.neutral.300}",
      "type": "color"
    },
    "on-surface-variant": {
      "value": "{color.neutral.800}",
      "type": "color"
    },
    "inverse-surface": {
      "value": "{color.neutral.900}",
      "type": "color"
    },
    "inverse-on-surface": {
      "value": "{color.neutral.100}",
      "type": "color"
    },
    "inverse-primary": {
      "value": "{color.primary.400}",
      "type": "color"
    },
    "shadow": {
      "value": "{color.black}",
      "type": "color"
    },
    "surface-tint": {
      "value": "{color.primary.800}",
      "type": "color"
    },
    "outline-variant": {
      "value": "{color.neutral.300}",
      "type": "color"
    },
    "scrim": {
      "value": "{color.black}",
      "type": "color"
    },
    "surface-container-highest": {
      "value": "{color.neutral.220}",
      "type": "color"
    },
    "surface-container-high": {
      "value": "{color.neutral.170}",
      "type": "color"
    },
    "surface-container": {
      "value": "{color.neutral.120}",
      "type": "color"
    },
    "surface-container-low": {
      "value": "{color.neutral.100}",
      "type": "color"
    },
    "surface-container-lowest": {
      "value": "{color.neutral.40}",
      "type": "color"
    },
    "surface-bright": {
      "value": "{color.neutral.240}",
      "type": "color"
    },
    "surface-dim": {
      "value": "{color.neutral.60}",
      "type": "color"
    }
  },
  "state-layers": {
    "primary": {
      "12": {
        "value": "{opacity.primary.800.12}",
        "type": "color"
      },
      "16": {
        "value": "{opacity.primary.800.16}",
        "type": "color"
      },
      "08": {
        "value": "{opacity.primary.800.08}",
        "type": "color"
      }
    },
    "on-primary": {
      "12": {
        "value": "{opacity.primary.200.12}",
        "type": "color"
      },
      "16": {
        "value": "{opacity.primary.200.16}",
        "type": "color"
      },
      "08": {
        "value": "{opacity.primary.200.08}",
        "type": "color"
      }
    },
    "primary-container": {
      "12": {
        "value": "{opacity.primary.300.12}",
        "type": "color"
      },
      "16": {
        "value": "{opacity.primary.300.16}",
        "type": "color"
      },
      "08": {
        "value": "{opacity.primary.300.08}",
        "type": "color"
      }
    },
    "on-primary-container": {
      "12": {
        "value": "{opacity.primary.900.12}",
        "type": "color"
      },
      "16": {
        "value": "{opacity.primary.900.16}",
        "type": "color"
      },
      "08": {
        "value": "{opacity.primary.900.08}",
        "type": "color"
      }
    },
    "primary-fixed": {
      "12": {
        "value": "{opacity.primary.900.12}",
        "type": "color"
      },
      "16": {
        "value": "{opacity.primary.900.16}",
        "type": "color"
      },
      "08": {
        "value": "{opacity.primary.900.08}",
        "type": "color"
      }
    },
    "on-primary-fixed": {
      "12": {
        "value": "{opacity.primary.100.12}",
        "type": "color"
      },
      "16": {
        "value": "{opacity.primary.100.16}",
        "type": "color"
      },
      "08": {
        "value": "{opacity.primary.100.08}",
        "type": "color"
      }
    },
    "primary-fixed-dim": {
      "12": {
        "value": "{opacity.primary.800.12}",
        "type": "color"
      },
      "16": {
        "value": "{opacity.primary.800.16}",
        "type": "color"
      },
      "08": {
        "value": "{opacity.primary.800.08}",
        "type": "color"
      }
    },
    "on-primary-fixed-variant": {
      "12": {
        "value": "{opacity.primary.300.12}",
        "type": "color"
      },
      "16": {
        "value": "{opacity.primary.300.16}",
        "type": "color"
      },
      "08": {
        "value": "{opacity.primary.300.08}",
        "type": "color"
      }
    },
    "secondary": {
      "12": {
        "value": "{opacity.secondary.800.12}",
        "type": "color"
      },
      "16": {
        "value": "{opacity.secondary.800.16}",
        "type": "color"
      },
      "08": {
        "value": "{opacity.secondary.800.08}",
        "type": "color"
      }
    },
    "on-secondary": {
      "12": {
        "value": "{opacity.secondary.200.12}",
        "type": "color"
      },
      "16": {
        "value": "{opacity.secondary.200.16}",
        "type": "color"
      },
      "08": {
        "value": "{opacity.secondary.200.08}",
        "type": "color"
      }
    },
    "secondary-container": {
      "12": {
        "value": "{opacity.secondary.300.12}",
        "type": "color"
      },
      "16": {
        "value": "{opacity.secondary.300.16}",
        "type": "color"
      },
      "08": {
        "value": "{opacity.secondary.300.08}",
        "type": "color"
      }
    },
    "on-secondary-container": {
      "12": {
        "value": "{opacity.secondary.900.12}",
        "type": "color"
      },
      "16": {
        "value": "{opacity.secondary.900.16}",
        "type": "color"
      },
      "08": {
        "value": "{opacity.secondary.900.08}",
        "type": "color"
      }
    },
    "secondary-fixed": {
      "12": {
        "value": "{opacity.secondary.900.12}",
        "type": "color"
      },
      "16": {
        "value": "{opacity.secondary.900.16}",
        "type": "color"
      },
      "08": {
        "value": "{opacity.secondary.900.08}",
        "type": "color"
      }
    },
    "on-secondary-fixed": {
      "12": {
        "value": "{opacity.secondary.100.12}",
        "type": "color"
      },
      "16": {
        "value": "{opacity.secondary.100.16}",
        "type": "color"
      },
      "08": {
        "value": "{opacity.secondary.100.08}",
        "type": "color"
      }
    },
    "secondary-fixed-dim": {
      "12": {
        "value": "{opacity.secondary.800.12}",
        "type": "color"
      },
      "16": {
        "value": "{opacity.secondary.800.16}",
        "type": "color"
      },
      "08": {
        "value": "{opacity.secondary.800.08}",
        "type": "color"
      }
    },
    "on-secondary-fixed-variant": {
      "12": {
        "value": "{opacity.secondary.300.12}",
        "type": "color"
      },
      "16": {
        "value": "{opacity.secondary.300.16}",
        "type": "color"
      },
      "08": {
        "value": "{opacity.secondary.300.08}",
        "type": "color"
      }
    },
    "error": {
      "12": {
        "value": "{opacity.error.800.12}",
        "type": "color"
      },
      "16": {
        "value": "{opacity.error.800.16}",
        "type": "color"
      },
      "08": {
        "value": "{opacity.error.800.08}",
        "type": "color"
      }
    },
    "error-container": {
      "12": {
        "value": "{opacity.error.300.12}",
        "type": "color"
      },
      "16": {
        "value": "{opacity.error.300.16}",
        "type": "color"
      },
      "08": {
        "value": "{opacity.error.300.08}",
        "type": "color"
      }
    },
    "on-error": {
      "12": {
        "value": "{opacity.error.200.12}",
        "type": "color"
      },
      "16": {
        "value": "{opacity.error.200.16}",
        "type": "color"
      },
      "08": {
        "value": "{opacity.error.200.08}",
        "type": "color"
      }
    },
    "on-error-container": {
      "12": {
        "value": "{opacity.error.900.12}",
        "type": "color"
      },
      "16": {
        "value": "{opacity.error.900.16}",
        "type": "color"
      },
      "08": {
        "value": "{opacity.error.900.08}",
        "type": "color"
      }
    },
    "background": {
      "12": {
        "value": "{opacity.neutral.100.12}",
        "type": "color"
      },
      "16": {
        "value": "{opacity.neutral.100.16}",
        "type": "color"
      },
      "08": {
        "value": "{opacity.neutral.100.08}",
        "type": "color"
      }
    },
    "on-background": {
      "12": {
        "value": "{opacity.neutral.900.12}",
        "type": "color"
      },
      "16": {
        "value": "{opacity.neutral.900.16}",
        "type": "color"
      },
      "08": {
        "value": "{opacity.neutral.900.08}",
        "type": "color"
      }
    },
    "outline": {
      "12": {
        "value": "{opacity.neutral.600.12}",
        "type": "color"
      },
      "16": {
        "value": "{opacity.neutral.600.16}",
        "type": "color"
      },
      "08": {
        "value": "{opacity.neutral.600.08}",
        "type": "color"
      }
    },
    "inverse-on-surface": {
      "12": {
        "value": "{opacity.neutral.100.12}",
        "type": "color"
      },
      "16": {
        "value": "{opacity.neutral.100.16}",
        "type": "color"
      },
      "08": {
        "value": "{opacity.neutral.100.08}",
        "type": "color"
      }
    },
    "inverse-surface": {
      "12": {
        "value": "{opacity.neutral.900.12}",
        "type": "color"
      },
      "16": {
        "value": "{opacity.neutral.900.16}",
        "type": "color"
      },
      "08": {
        "value": "{opacity.neutral.900.08}",
        "type": "color"
      }
    },
    "inverse-primary": {
      "12": {
        "value": "{opacity.primary.400.12}",
        "type": "color"
      },
      "16": {
        "value": "{opacity.primary.400.16}",
        "type": "color"
      },
      "08": {
        "value": "{opacity.primary.400.08}",
        "type": "color"
      }
    },
    "shadow": {
      "12": {
        "value": "{opacity.black.12}",
        "type": "color"
      },
      "16": {
        "value": "{opacity.black.16}",
        "type": "color"
      },
      "08": {
        "value": "{opacity.black.08}",
        "type": "color"
      }
    },
    "surface-tint": {
      "12": {
        "value": "{opacity.primary.800.12}",
        "type": "color"
      },
      "16": {
        "value": "{opacity.primary.800.16}",
        "type": "color"
      },
      "08": {
        "value": "{opacity.primary.800.08}",
        "type": "color"
      }
    },
    "outline-variant": {
      "12": {
        "value": "{opacity.neutral.300.12}",
        "type": "color"
      },
      "16": {
        "value": "{opacity.neutral.300.16}",
        "type": "color"
      },
      "08": {
        "value": "{opacity.neutral.300.08}",
        "type": "color"
      }
    },
    "scrim": {
      "12": {
        "value": "{opacity.white.12}",
        "type": "color"
      },
      "16": {
        "value": "{opacity.white.16}",
        "type": "color"
      },
      "08": {
        "value": "{opacity.white.08}",
        "type": "color"
      }
    },
    "surface": {
      "12": {
        "value": "{opacity.neutral.60.12}",
        "type": "color"
      },
      "16": {
        "value": "{opacity.neutral.60.16}",
        "type": "color"
      },
      "08": {
        "value": "{opacity.neutral.60.08}",
        "type": "color"
      }
    },
    "on-surface": {
      "12": {
        "value": "{opacity.neutral.800.12}",
        "type": "color"
      },
      "16": {
        "value": "{opacity.neutral.800.16}",
        "type": "color"
      },
      "08": {
        "value": "{opacity.neutral.800.08}",
        "type": "color"
      }
    },
    "surface-variant": {
      "12": {
        "value": "{opacity.neutral.300.12}",
        "type": "color"
      },
      "16": {
        "value": "{opacity.neutral.300.16}",
        "type": "color"
      },
      "08": {
        "value": "{opacity.neutral.300.08}",
        "type": "color"
      }
    },
    "on-surface-variant": {
      "12": {
        "value": "{opacity.neutral.800.12}",
        "type": "color"
      },
      "16": {
        "value": "{opacity.neutral.800.16}",
        "type": "color"
      },
      "08": {
        "value": "{opacity.neutral.800.08}",
        "type": "color"
      }
    },
    "surface-container-highest": {
      "12": {
        "value": "{opacity.neutral.220.12}",
        "type": "color"
      },
      "16": {
        "value": "{opacity.neutral.220.16}",
        "type": "color"
      },
      "08": {
        "value": "{opacity.neutral.220.08}",
        "type": "color"
      }
    },
    "surface-container-high": {
      "12": {
        "value": "{opacity.neutral.170.12}",
        "type": "color"
      },
      "16": {
        "value": "{opacity.neutral.170.16}",
        "type": "color"
      },
      "08": {
        "value": "{opacity.neutral.170.08}",
        "type": "color"
      }
    },
    "surface-container": {
      "12": {
        "value": "{opacity.neutral.120.12}",
        "type": "color"
      },
      "16": {
        "value": "{opacity.neutral.120.16}",
        "type": "color"
      },
      "08": {
        "value": "{opacity.neutral.120.08}",
        "type": "color"
      }
    },
    "surface-container-low": {
      "12": {
        "value": "{opacity.neutral.100.12}",
        "type": "color"
      },
      "16": {
        "value": "{opacity.neutral.100.16}",
        "type": "color"
      },
      "08": {
        "value": "{opacity.neutral.100.08}",
        "type": "color"
      }
    },
    "surface-container-lowest": {
      "12": {
        "value": "{opacity.neutral.40.12}",
        "type": "color"
      },
      "16": {
        "value": "{opacity.neutral.40.16}",
        "type": "color"
      },
      "08": {
        "value": "{opacity.neutral.40.08}",
        "type": "color"
      }
    },
    "surface-dim": {
      "12": {
        "value": "{opacity.neutral.60.12}",
        "type": "color"
      },
      "16": {
        "value": "{opacity.neutral.60.16}",
        "type": "color"
      },
      "08": {
        "value": "{opacity.neutral.60.08}",
        "type": "color"
      }
    },
    "surface-bright": {
      "12": {
        "value": "{opacity.neutral.240.12}",
        "type": "color"
      },
      "16": {
        "value": "{opacity.neutral.240.16}",
        "type": "color"
      },
      "08": {
        "value": "{opacity.neutral.240.08}",
        "type": "color"
      }
    }
  },
  "shadows": {
    "15": {
      "value": "{opacity.black.15}",
      "type": "color"
    },
    "30": {
      "value": "{opacity.black.30}",
      "type": "color"
    }
  },
  "elevations": {
    "1": {
      "value": [
        {
          "color": "{shadows.medium}",
          "type": "dropShadow",
          "x": "0",
          "y": "1",
          "blur": "3",
          "spread": "1"
        },
        {
          "color": "{shadows.strong}",
          "type": "dropShadow",
          "x": "0",
          "y": "1",
          "blur": "2",
          "spread": "0"
        }
      ],
      "type": "boxShadow"
    },
    "2": {
      "value": [
        {
          "color": "{shadows.medium}",
          "type": "dropShadow",
          "x": "0",
          "y": "2",
          "blur": "6",
          "spread": "2"
        },
        {
          "color": "{shadows.strong}",
          "type": "dropShadow",
          "x": "0",
          "y": "1",
          "blur": "2",
          "spread": "0"
        }
      ],
      "type": "boxShadow"
    },
    "3": {
      "value": [
        {
          "color": "{shadows.medium}",
          "type": "dropShadow",
          "x": "0",
          "y": "4",
          "blur": "8",
          "spread": "3"
        },
        {
          "color": "{shadows.strong}",
          "type": "dropShadow",
          "x": "0",
          "y": "1",
          "blur": "3",
          "spread": "0"
        }
      ],
      "type": "boxShadow"
    },
    "4": {
      "value": [
        {
          "color": "{shadows.medium}",
          "type": "dropShadow",
          "x": "0",
          "y": "6",
          "blur": "10",
          "spread": "4"
        },
        {
          "color": "{shadows.strong}",
          "type": "dropShadow",
          "x": "0",
          "y": "2",
          "blur": "3",
          "spread": "0"
        }
      ],
      "type": "boxShadow"
    },
    "5": {
      "value": [
        {
          "color": "{shadows.medium}",
          "type": "dropShadow",
          "x": "0",
          "y": "8",
          "blur": "12",
          "spread": "6"
        },
        {
          "color": "{shadows.strong}",
          "type": "dropShadow",
          "x": "0",
          "y": "4",
          "blur": "4",
          "spread": "0"
        }
      ],
      "type": "boxShadow"
    }
  }
}